[{"match_id": 2259035, "stats": {"MIN": 90, "GL": 0, "ASS": 0, "CS": 0, "SV": 0, "PE": 0, "PS": 0, "PM": 0, "GC": 1, "YC": 0, "RC": 0, "OG": 0, "OGA": 0, "SH": 0, "WF": 0, "PSS": 42, "APS": 26, "CRS": 0, "KP": 0, "BC": 0, "CL": 1, "BLK": 0, "INT": 0, "TCK": 0, "BR": 5, "ELG": 0}}, {"match_id": 2259045, "stats": {"MIN": 90, "GL": 0, "ASS": 0, "CS": 0, "SV": 0, "PE": 0, "PS": 0, "PM": 0, "GC": 3, "YC": 0, "RC": 0, "OG": 0, "OGA": 0, "SH": 0, "WF": 0, "PSS": 28, "APS": 26, "CRS": 0, "KP": 0, "BC": 0, "CL": 1, "BLK": 0, "INT": 0, "TCK": 0, "BR": 5, "ELG": 0}}, {"match_id": 2261025, "stats": {"MIN": 90, "GL": 0, "ASS": 0, "CS": 0, "SV": 6, "PE": 0, "PS": 0, "PM": 0, "GC": 1, "YC": 0, "RC": 0, "OG": 0, "OGA": 0, "SH": 0, "WF": 0, "PSS": 39, "APS": 34, "CRS": 0, "KP": 0, "BC": 0, "CL": 1, "BLK": 0, "INT": 0, "TCK": 0, "BR": 10, "ELG": 0}}, {"match_id": 2261027, "stats": {"MIN": 90, "GL": 0, "ASS": 0, "CS": 0, "SV": 3, "PE": 0, "PS": 0, "PM": 0, "GC": 3, "YC": 0, "RC": 0, "OG": 0, "OGA": 0, "SH": 0, "WF": 0, "PSS": 24, "APS": 22, "CRS": 0, "KP": 0, "BC": 0, "CL": 0, "BLK": 0, "INT": 0, "TCK": 0, "BR": 10, "ELG": 0}}, {"match_id": 2261049, "stats": {"MIN": 90, "GL": 0, "ASS": 0, "CS": 1, "SV": 2, "PE": 0, "PS": 0, "PM": 0, "GC": 0, "YC": 0, "RC": 0, "OG": 0, "OGA": 0, "SH": 0, "WF": 0, "PSS": 32, "APS": 17, "CRS": 0, "KP": 0, "BC": 0, "CL": 1, "BLK": 0, "INT": 0, "TCK": 0, "BR": 11, "ELG": 0}}, {"match_id": 2261058, "stats": {"MIN": 90, "GL": 0, "ASS": 0, "CS": 0, "SV": 3, "PE": 0, "PS": 0, "PM": 0, "GC": 1, "YC": 0, "RC": 0, "OG": 0, "OGA": 0, "SH": 0, "WF": 0, "PSS": 28, "APS": 24, "CRS": 0, "KP": 0, "BC": 0, "CL": 0, "BLK": 0, "INT": 0, "TCK": 0, "BR": 9, "ELG": 0}}, {"match_id": 2261072, "stats": {"MIN": 73, "GL": 0, "ASS": 0, "CS": 1, "SV": 0, "PE": 0, "PS": 0, "PM": 0, "GC": 0, "YC": 0, "RC": 0, "OG": 0, "OGA": 0, "SH": 0, "WF": 0, "PSS": 18, "APS": 16, "CRS": 0, "KP": 0, "BC": 0, "CL": 1, "BLK": 0, "INT": 0, "TCK": 0, "BR": 6, "ELG": 0}}, {"round_id": "all", "stats": {"MIN": 613, "GL": 0, "ASS": 0, "CS": 2, "SV": 14, "PE": 0, "PS": 0, "PM": 0, "GC": 9, "YC": 0, "RC": 0, "OG": 0, "OGA": 0, "SH": 0, "WF": 0, "PSS": 211, "APS": 165, "CRS": 0, "KP": 0, "BC": 0, "CL": 5, "BLK": 0, "INT": 0, "TCK": 0, "BR": 56, "ELG": 0}}]