[{"stats": {"WF": 0, "MIN": 11, "CRS": 0, "YC": 0, "BR": 0, "ASS": 0, "PS": 0, "BC": 0, "SH": 0, "TCK": 0, "RC": 0, "PM": 0, "CL": 0, "PE": 0, "ELG": 0, "GC": 0, "BLK": 0, "CS": 1, "GL": 0, "OG": 0, "APS": 1, "SV": 0, "INT": 0, "KP": 0, "PSS": 1, "OGA": 0}, "match_id": 1039932}, {"stats": {"WF": 1, "MIN": 25, "CRS": 0, "YC": 0, "BR": 3, "ASS": 0, "PS": 0, "BC": 0, "SH": 0, "TCK": 0, "RC": 0, "PM": 0, "CL": 0, "PE": 0, "ELG": 0, "GC": 0, "BLK": 0, "CS": 1, "GL": 0, "OG": 0, "APS": 7, "SV": 0, "INT": 0, "KP": 1, "PSS": 9, "OGA": 0}, "match_id": 1039944}, {"stats": {"WF": 1, "MIN": 74, "CRS": 0, "YC": 0, "BR": 2, "ASS": 0, "PS": 0, "BC": 0, "SH": 0, "TCK": 0, "RC": 0, "PM": 0, "CL": 0, "PE": 0, "ELG": 0, "GC": 1, "BLK": 0, "CS": 0, "GL": 0, "OG": 0, "APS": 11, "SV": 0, "INT": 1, "KP": 1, "PSS": 16, "OGA": 0}, "match_id": 1039994}, {"stats": {"WF": 0, "MIN": 90, "CRS": 0, "YC": 0, "BR": 2, "ASS": 0, "PS": 0, "BC": 0, "SH": 0, "TCK": 1, "RC": 0, "PM": 0, "CL": 0, "PE": 0, "ELG": 0, "GC": 2, "BLK": 0, "CS": 0, "GL": 0, "OG": 0, "APS": 19, "SV": 0, "INT": 2, "KP": 0, "PSS": 28, "OGA": 0}, "match_id": 1040009}, {"stats": {"WF": 0, "MIN": 90, "CRS": 0, "YC": 0, "BR": 1, "ASS": 0, "PS": 0, "BC": 0, "SH": 1, "TCK": 0, "RC": 0, "PM": 0, "CL": 3, "PE": 0, "ELG": 0, "GC": 0, "BLK": 0, "CS": 1, "GL": 1, "OG": 0, "APS": 6, "SV": 0, "INT": 1, "KP": 0, "PSS": 9, "OGA": 0}, "match_id": 1040021}, {"stats": {"WF": 0, "MIN": 5, "CRS": 0, "YC": 0, "BR": 0, "ASS": 0, "PS": 0, "BC": 0, "SH": 0, "TCK": 0, "RC": 0, "PM": 0, "CL": 1, "PE": 0, "ELG": 0, "GC": 0, "BLK": 0, "CS": 1, "GL": 0, "OG": 0, "APS": 0, "SV": 0, "INT": 0, "KP": 0, "PSS": 0, "OGA": 0}, "match_id": 1040042}, {"stats": {"WF": 3, "MIN": 90, "CRS": 0, "YC": 0, "BR": 4, "ASS": 0, "PS": 0, "BC": 0, "SH": 0, "TCK": 0, "RC": 0, "PM": 0, "CL": 1, "PE": 0, "ELG": 0, "GC": 1, "BLK": 0, "CS": 0, "GL": 0, "OG": 0, "APS": 9, "SV": 0, "INT": 0, "KP": 0, "PSS": 18, "OGA": 0}, "match_id": 1040049}, {"stats": {"WF": 1, "MIN": 12, "CRS": 0, "YC": 0, "BR": 0, "ASS": 0, "PS": 0, "BC": 0, "SH": 0, "TCK": 0, "RC": 0, "PM": 0, "CL": 0, "PE": 0, "ELG": 0, "GC": 0, "BLK": 0, "CS": 1, "GL": 0, "OG": 0, "APS": 2, "SV": 0, "INT": 0, "KP": 0, "PSS": 3, "OGA": 0}, "match_id": 1040117}, {"round_id": "all", "stats": {"WF": 6, "MIN": 397, "CRS": 0, "YC": 0, "BR": 12, "ASS": 0, "PS": 0, "BC": 0, "SH": 1, "TCK": 1, "RC": 0, "PM": 0, "CL": 5, "PE": 0, "ELG": 0, "GC": 4, "BLK": 0, "CS": 5, "GL": 1, "OG": 0, "APS": 55, "SV": 0, "INT": 4, "KP": 2, "PSS": 84, "OGA": 0}}]