[{"stats": {"WF": 2, "MIN": 74, "CRS": 0, "YC": 0, "BR": 1, "ASS": 0, "PS": 0, "BC": 1, "SH": 2, "TCK": 0, "RC": 0, "PM": 0, "CL": 1, "PE": 0, "ELG": 0, "GC": 2, "BLK": 0, "CS": 0, "GL": 0, "OG": 0, "APS": 27, "SV": 0, "INT": 1, "KP": 1, "PSS": 32, "OGA": 0}, "match_id": 1037575}, {"stats": {"WF": 0, "MIN": 11, "CRS": 0, "YC": 0, "BR": 2, "ASS": 0, "PS": 0, "BC": 0, "SH": 0, "TCK": 1, "RC": 0, "PM": 0, "CL": 0, "PE": 0, "ELG": 0, "GC": 1, "BLK": 0, "CS": 0, "GL": 0, "OG": 0, "APS": 8, "SV": 0, "INT": 1, "KP": 0, "PSS": 10, "OGA": 0}, "match_id": 1037594}, {"stats": {"WF": 0, "MIN": 16, "CRS": 0, "YC": 0, "BR": 2, "ASS": 0, "PS": 0, "BC": 0, "SH": 2, "TCK": 0, "RC": 0, "PM": 0, "CL": 0, "PE": 0, "ELG": 0, "GC": 0, "BLK": 0, "CS": 1, "GL": 0, "OG": 0, "APS": 5, "SV": 0, "INT": 0, "KP": 0, "PSS": 6, "OGA": 0}, "match_id": 1039879}, {"stats": {"WF": 1, "MIN": 75, "CRS": 0, "YC": 0, "BR": 11, "ASS": 0, "PS": 0, "BC": 0, "SH": 1, "TCK": 2, "RC": 0, "PM": 0, "CL": 0, "PE": 0, "ELG": 0, "GC": 0, "BLK": 0, "CS": 1, "GL": 1, "OG": 0, "APS": 38, "SV": 0, "INT": 2, "KP": 1, "PSS": 49, "OGA": 0}, "match_id": 1039886}, {"stats": {"WF": 1, "MIN": 68, "CRS": 0, "YC": 0, "BR": 3, "ASS": 0, "PS": 0, "BC": 0, "SH": 0, "TCK": 1, "RC": 0, "PM": 0, "CL": 0, "PE": 0, "ELG": 0, "GC": 0, "BLK": 0, "CS": 1, "GL": 0, "OG": 0, "APS": 22, "SV": 0, "INT": 0, "KP": 1, "PSS": 23, "OGA": 0}, "match_id": 1039910}, {"stats": {"WF": 1, "MIN": 37, "CRS": 1, "YC": 0, "BR": 2, "ASS": 1, "PS": 0, "BC": 0, "SH": 3, "TCK": 1, "RC": 0, "PM": 0, "CL": 0, "PE": 0, "ELG": 0, "GC": 0, "BLK": 0, "CS": 1, "GL": 2, "OG": 0, "APS": 15, "SV": 0, "INT": 0, "KP": 4, "PSS": 19, "OGA": 0}, "match_id": 1039917}, {"stats": {"WF": 0, "MIN": 45, "CRS": 1, "YC": 0, "BR": 4, "ASS": 0, "PS": 0, "BC": 0, "SH": 1, "TCK": 1, "RC": 0, "PM": 0, "CL": 0, "PE": 0, "ELG": 0, "GC": 0, "BLK": 0, "CS": 1, "GL": 0, "OG": 0, "APS": 25, "SV": 0, "INT": 0, "KP": 1, "PSS": 27, "OGA": 0}, "match_id": 1039934}, {"stats": {"WF": 3, "MIN": 45, "CRS": 0, "YC": 1, "BR": 2, "ASS": 1, "PS": 0, "BC": 0, "SH": 0, "TCK": 1, "RC": 0, "PM": 0, "CL": 0, "PE": 0, "ELG": 0, "GC": 1, "BLK": 0, "CS": 0, "GL": 0, "OG": 0, "APS": 11, "SV": 0, "INT": 0, "KP": 0, "PSS": 17, "OGA": 0}, "match_id": 1039952}, {"stats": {"WF": 0, "MIN": 23, "CRS": 0, "YC": 0, "BR": 4, "ASS": 1, "PS": 0, "BC": 1, "SH": 0, "TCK": 0, "RC": 0, "PM": 0, "CL": 1, "PE": 0, "ELG": 0, "GC": 0, "BLK": 0, "CS": 1, "GL": 0, "OG": 0, "APS": 6, "SV": 0, "INT": 1, "KP": 1, "PSS": 10, "OGA": 0}, "match_id": 1039959}, {"stats": {"WF": 0, "MIN": 54, "CRS": 0, "YC": 1, "BR": 5, "ASS": 1, "PS": 0, "BC": 0, "SH": 2, "TCK": 1, "RC": 0, "PM": 0, "CL": 0, "PE": 0, "ELG": 0, "GC": 0, "BLK": 0, "CS": 1, "GL": 1, "OG": 0, "APS": 25, "SV": 0, "INT": 0, "KP": 1, "PSS": 29, "OGA": 0}, "match_id": 1039972}, {"stats": {"WF": 3, "MIN": 33, "CRS": 0, "YC": 0, "BR": 0, "ASS": 0, "PS": 0, "BC": 0, "SH": 0, "TCK": 0, "RC": 0, "PM": 0, "CL": 0, "PE": 0, "ELG": 0, "GC": 0, "BLK": 0, "CS": 1, "GL": 0, "OG": 0, "APS": 28, "SV": 0, "INT": 0, "KP": 2, "PSS": 33, "OGA": 0}, "match_id": 1040027}, {"stats": {"WF": 2, "MIN": 45, "CRS": 0, "YC": 0, "BR": 1, "ASS": 0, "PS": 0, "BC": 0, "SH": 0, "TCK": 0, "RC": 0, "PM": 0, "CL": 0, "PE": 0, "ELG": 0, "GC": 1, "BLK": 0, "CS": 0, "GL": 0, "OG": 0, "APS": 22, "SV": 0, "INT": 0, "KP": 0, "PSS": 25, "OGA": 0}, "match_id": 1040095}, {"stats": {"WF": 2, "MIN": 67, "CRS": 1, "YC": 0, "BR": 4, "ASS": 0, "PS": 0, "BC": 0, "SH": 2, "TCK": 0, "RC": 0, "PM": 0, "CL": 0, "PE": 0, "ELG": 0, "GC": 0, "BLK": 0, "CS": 1, "GL": 0, "OG": 0, "APS": 26, "SV": 0, "INT": 1, "KP": 4, "PSS": 34, "OGA": 0}, "match_id": 1040104}, {"stats": {"WF": 0, "MIN": 4, "CRS": 0, "YC": 0, "BR": 2, "ASS": 1, "PS": 0, "BC": 1, "SH": 0, "TCK": 0, "RC": 0, "PM": 0, "CL": 0, "PE": 0, "ELG": 0, "GC": 0, "BLK": 0, "CS": 1, "GL": 0, "OG": 0, "APS": 3, "SV": 0, "INT": 1, "KP": 1, "PSS": 4, "OGA": 0}, "match_id": 1040111}, {"stats": {"WF": 0, "MIN": 22, "CRS": 0, "YC": 0, "BR": 2, "ASS": 1, "PS": 0, "BC": 0, "SH": 0, "TCK": 1, "RC": 0, "PM": 0, "CL": 2, "PE": 0, "ELG": 0, "GC": 0, "BLK": 0, "CS": 1, "GL": 0, "OG": 0, "APS": 16, "SV": 0, "INT": 0, "KP": 2, "PSS": 18, "OGA": 0}, "match_id": 1040124}, {"stats": {"WF": 0, "MIN": 21, "CRS": 0, "YC": 0, "BR": 2, "ASS": 0, "PS": 0, "BC": 0, "SH": 1, "TCK": 1, "RC": 0, "PM": 0, "CL": 0, "PE": 0, "ELG": 0, "GC": 0, "BLK": 0, "CS": 1, "GL": 0, "OG": 0, "APS": 11, "SV": 0, "INT": 0, "KP": 0, "PSS": 13, "OGA": 0}, "match_id": 1040138}, {"round_id": "all", "stats": {"WF": 15, "MIN": 640, "CRS": 3, "YC": 2, "BR": 47, "ASS": 6, "PS": 0, "BC": 3, "SH": 14, "TCK": 10, "RC": 0, "PM": 0, "CL": 4, "PE": 0, "ELG": 0, "GC": 5, "BLK": 0, "CS": 12, "GL": 4, "OG": 0, "APS": 288, "SV": 0, "INT": 7, "KP": 19, "PSS": 349, "OGA": 0}}]