[{"match_id": 2259031, "stats": {"MIN": 78, "GL": 0, "ASS": 0, "CS": 1, "SV": 0, "PE": 0, "PS": 0, "PM": 0, "GC": 0, "YC": 0, "RC": 0, "OG": 0, "OGA": 0, "SH": 1, "WF": 0, "PSS": 19, "APS": 12, "CRS": 0, "KP": 0, "BC": 0, "CL": 2, "BLK": 0, "INT": 2, "TCK": 2, "BR": 4, "ELG": 0}}, {"match_id": 2261013, "stats": {"MIN": 45, "GL": 0, "ASS": 0, "CS": 0, "SV": 0, "PE": 0, "PS": 0, "PM": 0, "GC": 2, "YC": 0, "RC": 0, "OG": 0, "OGA": 0, "SH": 0, "WF": 0, "PSS": 8, "APS": 6, "CRS": 1, "KP": 0, "BC": 0, "CL": 1, "BLK": 0, "INT": 0, "TCK": 3, "BR": 1, "ELG": 0}}, {"round_id": "all", "stats": {"MIN": 123, "GL": 0, "ASS": 0, "CS": 1, "SV": 0, "PE": 0, "PS": 0, "PM": 0, "GC": 2, "YC": 0, "RC": 0, "OG": 0, "OGA": 0, "SH": 1, "WF": 0, "PSS": 27, "APS": 18, "CRS": 1, "KP": 0, "BC": 0, "CL": 3, "BLK": 0, "INT": 2, "TCK": 5, "BR": 5, "ELG": 0}}]